{
  "storyflag": -1,
  "storyflagindex": -1,
  "incstoryflag": false,
  "incstoryflagindex": false,
  "music": "",
  "teleportsplayer": true,
  "playercoordinatesx": -155.6,
  "playercoordinatesy": 1,
  "playercoordinatesz": -111.2,
  "playerrotation": 0,
  "playermovement": "",
  "interactioncutscene": [],
  "interactionregular": [
    "Sam",

    "Are you crazy, dude...? A lil' slip and we'd be crushed like a bug.",
    ",CharSamSpeaking",
    ""
  ],
  "interactionpickupitem": [],
  "collectibleitemid": "",
  "warpdata": "",
  "battlesdata": false,
  "storymode": true,
  "explorationmode": true,
  "repeat": true
}
